{
  "project_info": {
    "project_number": "455331973314",
    "project_id": "wastemanagement-60c33",
    "storage_bucket": "wastemanagement-60c33.firebasestorage.app"
  },
  "client": [
    {
      "client_info": {
        "mobilesdk_app_id": "1:455331973314:android:2d9604a150e5de4262535b",
        "android_client_info": {
          "package_name": "com.example.waste_management_system_mobileapp"
        }
      },
      "oauth_client": [],
      "api_key": [
        {
          "current_key": "AIzaSyBfuhkFaWb8JNVGTXxe6s_D7Keb0L1_ZyU"
        }
      ],
      "services": {
        "appinvite_service": {
          "other_platform_oauth_client": []
        }
      }
    }
  ],
  "configuration_version": "1"
}